djangocms_maps/__init__.py
djangocms_maps/cms_plugins.py
djangocms_maps/forms.py
djangocms_maps/models.py
djangocms_maps/settings.py
djangocms_maps/locale/af/LC_MESSAGES/django.mo
djangocms_maps/locale/af/LC_MESSAGES/django.po
djangocms_maps/locale/ar/LC_MESSAGES/django.mo
djangocms_maps/locale/ar/LC_MESSAGES/django.po
djangocms_maps/locale/be/LC_MESSAGES/django.mo
djangocms_maps/locale/be/LC_MESSAGES/django.po
djangocms_maps/locale/bg/LC_MESSAGES/django.mo
djangocms_maps/locale/bg/LC_MESSAGES/django.po
djangocms_maps/locale/bn/LC_MESSAGES/django.mo
djangocms_maps/locale/bn/LC_MESSAGES/django.po
djangocms_maps/locale/ca/LC_MESSAGES/django.mo
djangocms_maps/locale/ca/LC_MESSAGES/django.po
djangocms_maps/locale/cmn/LC_MESSAGES/django.mo
djangocms_maps/locale/cmn/LC_MESSAGES/django.po
djangocms_maps/locale/cs/LC_MESSAGES/django.mo
djangocms_maps/locale/cs/LC_MESSAGES/django.po
djangocms_maps/locale/cy/LC_MESSAGES/django.mo
djangocms_maps/locale/cy/LC_MESSAGES/django.po
djangocms_maps/locale/da/LC_MESSAGES/django.mo
djangocms_maps/locale/da/LC_MESSAGES/django.po
djangocms_maps/locale/de/LC_MESSAGES/django.mo
djangocms_maps/locale/de/LC_MESSAGES/django.po
djangocms_maps/locale/el/LC_MESSAGES/django.mo
djangocms_maps/locale/el/LC_MESSAGES/django.po
djangocms_maps/locale/en/LC_MESSAGES/django.mo
djangocms_maps/locale/en/LC_MESSAGES/django.po
djangocms_maps/locale/es/LC_MESSAGES/django.mo
djangocms_maps/locale/es/LC_MESSAGES/django.po
djangocms_maps/locale/es_AR/LC_MESSAGES/django.mo
djangocms_maps/locale/es_AR/LC_MESSAGES/django.po
djangocms_maps/locale/es_BO/LC_MESSAGES/django.mo
djangocms_maps/locale/es_BO/LC_MESSAGES/django.po
djangocms_maps/locale/es_DO/LC_MESSAGES/django.mo
djangocms_maps/locale/es_DO/LC_MESSAGES/django.po
djangocms_maps/locale/et/LC_MESSAGES/django.mo
djangocms_maps/locale/et/LC_MESSAGES/django.po
djangocms_maps/locale/eu/LC_MESSAGES/django.mo
djangocms_maps/locale/eu/LC_MESSAGES/django.po
djangocms_maps/locale/fa/LC_MESSAGES/django.mo
djangocms_maps-0.13.0.dist-info/LICENSE.txt
djangocms_maps-0.13.0.dist-info/METADATA
djangocms_maps-0.13.0.dist-info/WHEEL
djangocms_maps-0.13.0.dist-info/top_level.txt
djangocms_maps-0.13.0.dist-info/RECORD
